[{"playerName":"Kagiso Rabada","runs":"0","balls":"0","sixes":"0","fours":"0","sr":"0.00","mYteamName":"Delhi Capitals","opponentTeamName":"Delhi Capitals","venue":" Dubai","date":" Nov 10 2020","resultOfmatch":"Mum Indians won by 5 wickets (with 8 balls remaining)"},{"playerName":"Kagiso Rabada","runs":"12","balls":"7","sixes":"1","fours":"0","sr":"171.43","mYteamName":"Delhi Capitals","opponentTeamName":"Delhi Capitals","venue":" Dubai","date":" Oct 31 2020","resultOfmatch":"Mum Indians won by 9 wickets (with 34 balls remaining)"},{"playerName":"Kagiso Rabada","runs":"15","balls":"15","sixes":"0","fours":"2","sr":"100.00","mYteamName":"Delhi Capitals","opponentTeamName":"Mumbai Indians","venue":" Dubai","date":" Nov 5 2020","resultOfmatch":"Mum Indians won by 57 runs"},{"playerName":"Kagiso Rabada","runs":"3","balls":"7","sixes":"0","fours":"0","sr":"42.86","mYteamName":"Delhi Capitals","opponentTeamName":"Sunrisers Hyderabad","venue":" Dubai","date":" Oct 27 2020","resultOfmatch":"Sunrisers won by 88 runs"},{"playerName":"Kagiso Rabada","runs":"15","balls":"7","sixes":"1","fours":"1","sr":"214.29","mYteamName":"Delhi Capitals","opponentTeamName":"Sunrisers Hyderabad","venue":" Abu Dhabi","date":" Sep 29 2020","resultOfmatch":"Sunrisers won by 15 runs"},{"playerName":"Kagiso Rabada","runs":"2","balls":"3","sixes":"0","fours":"0","sr":"66.67","mYteamName":"Delhi Capitals","opponentTeamName":"Delhi Capitals","venue":" Sharjah","date":" Oct 9 2020","resultOfmatch":"Capitals won by 46 runs"},{"playerName":"Kagiso Rabada","runs":"0","balls":"0","sixes":"0","fours":"0","sr":"0.00","mYteamName":"Delhi Capitals","opponentTeamName":"Delhi Capitals","venue":" Dubai","date":" Sep 20 2020","resultOfmatch":"Match tied (Capitals won the one-over eliminator)"},{"playerName":"Kagiso Rabada","runs":"9","balls":"10","sixes":"0","fours":"1","sr":"90.00","mYteamName":"Delhi Capitals","opponentTeamName":"Kolkata Knight Riders","venue":" Abu Dhabi","date":" Oct 24 2020","resultOfmatch":"KKR won by 59 runs"}]